Workbook

Sheet data
A1: PRODUCT SALES | M1: EXERCISES
A3: Date | B3: Store number | C3: Area in sqm | D3: Zone | E3: Sales amount | F3: Over or Lower 530€ | G3: Sales incremented | H3: Discount | I3: Payment | J3: Age | M3: EASY LEVEL
A4: 44843 | B4: 1 | C4: =VLOOKUP(B4,'area in m2'!B$2:C$10,2,FALSE) -> 280 | D4: Center | E4: 533.62466 | F4: =IF(E4>530,"Over 530","Below 530") -> Over 530 | G4: =+E4*1.05 -> 560.3059 | H4: 0.01 | I4: Cash | J4: 46 | L4: 1 | M4: Number of sales transactions and average sales amount by Zone.
A5: 44786 | B5: 9 | C5: =VLOOKUP(B5,'area in m2'!B$2:C$10,2,FALSE) -> 140 | D5: North | E5: 521.93932 | F5: =IF(E5>530,"Over 530","Below 530") -> Below 530 | G5: =+E5*1.05 -> 548.03628 | H5: 0.02 | I5: Deferred | J5: 48 | L5: 2 | M5: Average sales amount per month and & % increase vs previous month
A6: 44682 | B6: 2 | C6: =VLOOKUP(B6,'area in m2'!B$2:C$10,2,FALSE) -> 250 | D6: Center | E6: 522.24338 | F6: =IF(E6>530,"Over 530","Below 530") -> Below 530 | G6: =+E6*1.05 -> 548.35555 | H6: 0 | I6: Deferred | J6: 49 | L6: 3 | M6: Same table but now with an increase of 5% in sales, by all stores.
A7: 44634 | B7: 9 | C7: =VLOOKUP(B7,'area in m2'!B$2:C$10,2,FALSE) -> 140 | D7: North | E7: 504.80304 | F7: =IF(E7>530,"Over 530","Below 530") -> Below 530 | G7: =+E7*1.05 -> 530.0432 | H7: 0.02 | I7: Cash | J7: 35
A8: 44888 | B8: 3 | C8: =VLOOKUP(B8,'area in m2'!B$2:C$10,2,FALSE) -> 195 | D8: Center | E8: 524.31074 | F8: =IF(E8>530,"Over 530","Below 530") -> Below 530 | G8: =+E8*1.05 -> 550.52627 | H8: 0.01 | I8: Cash | J8: 38 | M8: MEDIUM LEVEL
A9: 44631 | B9: 6 | C9: =VLOOKUP(B9,'area in m2'!B$2:C$10,2,FALSE) -> 175 | D9: South | E9: 505.40693 | F9: =IF(E9>530,"Over 530","Below 530") -> Below 530 | G9: =+E9*1.05 -> 530.67728 | H9: 0 | I9: Cash | J9: 40 | L9: 4 | M9: Calculate the number of transactions over 530€ per Zone and Store.
A10: 44807 | B10: 1 | C10: =VLOOKUP(B10,'area in m2'!B$2:C$10,2,FALSE) -> 280 | D10: Center | E10: 520.79123 | F10: =IF(E10>530,"Over 530","Below 530") -> Below 530 | G10: =+E10*1.05 -> 546.8308 | H10: 0.01 | I10: Cash | J10: 21 | L10: 5 | M10: Which age group has the highest average use of deferred payments: 20–29, 30–39, or over 50?
A11: 44919 | B11: 1 | C11: =VLOOKUP(B11,'area in m2'!B$2:C$10,2,FALSE) -> 280 | D11: Center | E11: 501.271 | F11: =IF(E11>530,"Over 530","Below 530") -> Below 530 | G11: =+E11*1.05 -> 526.33455 | H11: 0 | I11: Deferred | J11: 39 | L11: 6 | M11: Is there any relation between Total Sales and Area in squared meters of the stores?
A12: 44634 | B12: 9 | C12: =VLOOKUP(B12,'area in m2'!B$2:C$10,2,FALSE) -> 140 | D12: North | E12: 543.1856 | F12: =IF(E12>530,"Over 530","Below 530") -> Over 530 | G12: =+E12*1.05 -> 570.34488 | H12: 0.01 | I12: Cash | J12: 50
A13: 44734 | B13: 1 | C13: =VLOOKUP(B13,'area in m2'!B$2:C$10,2,FALSE) -> 280 | D13: Center | E13: 524.31993 | F13: =IF(E13>530,"Over 530","Below 530") -> Below 530 | G13: =+E13*1.05 -> 550.53593 | H13: 0.02 | I13: Cash | J13: 24
A14: 44680 | B14: 5 | C14: =VLOOKUP(B14,'area in m2'!B$2:C$10,2,FALSE) -> 200 | D14: South | E14: 521.06855 | F14: =IF(E14>530,"Over 530","Below 530") -> Below 530 | G14: =+E14*1.05 -> 547.12197 | H14: 0.02 | I14: Deferred | J14: 32
A15: 44878 | B15: 8 | C15: =VLOOKUP(B15,'area in m2'!B$2:C$10,2,FALSE) -> 142 | D15: North | E15: 507.96048 | F15: =IF(E15>530,"Over 530","Below 530") -> Below 530 | G15: =+E15*1.05 -> 533.35851 | H15: 0.01 | I15: Cash | J15: 29
A16: 44917 | B16: 6 | C16: =VLOOKUP(B16,'area in m2'!B$2:C$10,2,FALSE) -> 175 | D16: South | E16: 518.81312 | F16: =IF(E16>530,"Over 530","Below 530") -> Below 530 | G16: =+E16*1.05 -> 544.75378 | H16: 0.03 | I16: Cash | J16: 22
A17: 44736 | B17: 6 | C17: =VLOOKUP(B17,'area in m2'!B$2:C$10,2,FALSE) -> 175 | D17: South | E17: 519.04456 | F17: =IF(E17>530,"Over 530","Below 530") -> Below 530 | G17: =+E17*1.05 -> 544.99678 | H17: 0 | I17: Deferred | J17: 39
A18: 44695 | B18: 1 | C18: =VLOOKUP(B18,'area in m2'!B$2:C$10,2,FALSE) -> 280 | D18: Center | E18: 528.39736 | F18: =IF(E18>530,"Over 530","Below 530") -> Below 530 | G18: =+E18*1.05 -> 554.81723 | H18: 0 | I18: Cash | J18: 28
A19: 44568 | B19: 9 | C19: =VLOOKUP(B19,'area in m2'!B$2:C$10,2,FALSE) -> 140 | D19: North | E19: 510.44928 | F19: =IF(E19>530,"Over 530","Below 530") -> Below 530 | G19: =+E19*1.05 -> 535.97175 | H19: 0.03 | I19: Cash | J19: 46
A20: 44828 | B20: 2 | C20: =VLOOKUP(B20,'area in m2'!B$2:C$10,2,FALSE) -> 250 | D20: Center | E20: 506.83973 | F20: =IF(E20>530,"Over 530","Below 530") -> Below 530 | G20: =+E20*1.05 -> 532.18171 | H20: 0 | I20: Cash | J20: 34
A21: 44767 | B21: 7 | C21: =VLOOKUP(B21,'area in m2'!B$2:C$10,2,FALSE) -> 166 | D21: North | E21: 525.99557 | F21: =IF(E21>530,"Over 530","Below 530") -> Below 530 | G21: =+E21*1.05 -> 552.29535 | H21: 0.02 | I21: Deferred | J21: 36
A22: 44673 | B22: 4 | C22: =VLOOKUP(B22,'area in m2'!B$2:C$10,2,FALSE) -> 188 | D22: Center | E22: 504.4371 | F22: =IF(E22>530,"Over 530","Below 530") -> Below 530 | G22: =+E22*1.05 -> 529.65896 | H22: 0.02 | I22: Deferred | J22: 24
A23: 44763 | B23: 7 | C23: =VLOOKUP(B23,'area in m2'!B$2:C$10,2,FALSE) -> 166 | D23: Center | E23: 537.25821 | F23: =IF(E23>530,"Over 530","Below 530") -> Over 530 | G23: =+E23*1.05 -> 564.12113 | H23: 0.03 | I23: Deferred | J23: 21
... A1517: 44645 | B1517: 2 | C1517: =VLOOKUP(B1517,'area in m2'!B$2:C$10,2,FALSE) -> 250 | D1517: Center | E1517: 526.212 | F1517: =IF(E1517>530,"Over 530","Below 530") -> Below 530 | G1517: =+E1517*1.05 -> 552.5226 | H1517: 0 | I1517: Cash | J1517: 37

Sheet area in m2
B1: Store number | C1: Area (sqm)
B2: 1 | C2: 280
B3: 2 | C3: 250
B4: 3 | C4: 195
B5: 4 | C5: 188
B6: 5 | C6: 200
B7: 6 | C7: 175
B8: 7 | C8: 166
B9: 8 | C9: 142
B10: 9 | C10: 140

Sheet 1
A1: Number of sales transactions and average sales amount by Zone.
A3: Row Labels | B3: Number of transactions | C3: Average of Sales amount
A4: Center | B4: 769 | C4: 524.7009
A5: North | B5: 369 | C5: 526.49421
A6: South | B6: 376 | C6: 527.53706
A7: Grand Total | B7: 1514 | C7: 525.84233

Sheet 2
A1: Average sales amount per month and % increase vs previous month
A3: Row Labels | B3: Average of Sales amount | C3: % increase
A4: ene | B4: 526.59234
A5: feb | B5: 525.99609 | C5: -0.0011322917
A6: mar | B6: 524.53175 | C6: -0.0027839217
A7: abr | B7: 527.2829 | C7: 0.005244961
A8: may | B8: 524.02106 | C8: -0.0061861367
A9: jun | B9: 526.34177 | C9: 0.0044286537
A10: jul | B10: 525.86216 | C10: -0.0009112114
A11: ago | B11: 526.88598 | C11: 0.0019469359
A12: sep | B12: 524.66294 | C12: -0.0042192031
A13: oct | B13: 526.5391 | C13: 0.0035759274
A14: nov | B14: 525.65333 | C14: -0.0016822364
A15: dic | B15: 526.30904 | C15: 0.001247419
A16: Grand Total | B16: 525.84233

Sheet 3
A1: Same table but now with an increase of 5% in sales, by all stores.
A3: Row Labels | B3: Average of Sales incremented | C3: % increase
A4: ene | B4: 552.92196
A5: feb | B5: 552.29589 | C5: -0.0011322917
A6: mar | B6: 550.75834 | C6: -0.0027839217
A7: abr | B7: 553.64705 | C7: 0.005244961
A8: may | B8: 550.22211 | C8: -0.0061861367
A9: jun | B9: 552.65886 | C9: 0.0044286537
A10: jul | B10: 552.15527 | C10: -0.0009112114
A11: ago | B11: 553.23028 | C11: 0.0019469359
A12: sep | B12: 550.89609 | C12: -0.0042192031
A13: oct | B13: 552.86605 | C13: 0.0035759274
A14: nov | B14: 551.936 | C14: -0.0016822364
A15: dic | B15: 552.62449 | C15: 0.001247419
A16: Grand Total | B16: 552.13445

Sheet 4
A1: Calculate the number of transactions over 530€ per Zone and Store.
A3: Number of transactions | B3: Column Labels
A4: Row Labels | B4: Below 530 | C4: Over 530
A5: Center | B5: 468 | C5: 301
A6: 1 | B6: 112 | C6: 68
A7: 2 | B7: 109 | C7: 66
A8: 3 | B8: 125 | C8: 88
A9: 4 | B9: 94 | C9: 67
A10: 7 | B10: 6 | C10: 1
A11: 8 | B11: 22 | C11: 11
A12: North | B12: 201 | C12: 168
A13: 7 | B13: 70 | C13: 58
A14: 8 | B14: 68 | C14: 58
A15: 9 | B15: 63 | C15: 52
A16: South | B16: 199 | C16: 177
A17: 5 | B17: 44 | C17: 143
A18: 6 | B18: 155 | C18: 34
A19: Grand Total | B19: 868 | C19: 646

Sheet 5
A1: Which age group has the highest average use of deferred payments: 20–29, 30–39, or over 50?
A3: Payment | B3: Deferred
A5: Row Labels | B5: Average of Sales amount
A6: From 20 to 29 | B6: 526.00217
A7: From 30 to 39 | B7: 525.78353
A8: Other | B8: 524.97708
A9: Over 50 | B9: 524.93733
A10: Grand Total | B10: 525.35728

Sheet 6
A1: Is there any relation between Total Sales and Area in squared meters of the stores?
A3: Row Labels | B3: Sum of Sales amount | C3: Sum of Area in sqm
A4: 3 | B4: 111988.55 | C4: 41535
A5: 5 | B5: 100503.39 | C5: 37400 | E5: There appears to be some relation, but highest amount of sales (stores 3&5) are not from biggest stores (1 & 2)
A6: 6 | B6: 97850.546 | C6: 33075
A7: 1 | B7: 94226.401 | C7: 50400
A8: 2 | B8: 91721.493 | C8: 43750
A9: 4 | B9: 84598.988 | C9: 30268
A10: 8 | B10: 83547.149 | C10: 22578
A11: 7 | B11: 71186.44 | C11: 22410
A12: 9 | B12: 60502.332 | C12: 16100
A13: Grand Total | B13: 796125.29 | C13: 297516
